scantool/__init__.py
scantool/call_graph.py
scantool/code_map.py
scantool/directory_formatter.py
scantool/formatter.py
scantool/gitignore.py
scantool/glob_expander.py
scantool/preview.py
scantool/scanner.py
scantool/server.py
scantool/entropy/__init__.py
scantool/entropy/callgraph.py
scantool/entropy/core.py
scantool/languages/__init__.py
scantool/languages/base.py
scantool/languages/config.py
scantool/languages/cpp.py
scantool/languages/csharp.py
scantool/languages/css.py
scantool/languages/generic.py
scantool/languages/go.py
scantool/languages/html.py
scantool/languages/image.py
scantool/languages/java.py
scantool/languages/markdown.py
scantool/languages/models.py
scantool/languages/php.py
scantool/languages/python.py
scantool/languages/ruby.py
scantool/languages/rust.py
scantool/languages/scss.py
scantool/languages/skip_patterns.py
scantool/languages/sql.py
scantool/languages/swift.py
scantool/languages/text.py
scantool/languages/typescript.py
scantool/languages/zig.py
scantool-0.12.0.dist-info/METADATA
scantool-0.12.0.dist-info/WHEEL
scantool-0.12.0.dist-info/entry_points.txt
scantool-0.12.0.dist-info/licenses/LICENSE
scantool-0.12.0.dist-info/RECORD
