Metadata-Version: 2.4
Name: scantool
Version: 0.12.0
Summary: MCP server for multi-language code analysis with structure extraction, metadata parsing, and search capabilities across Python, JavaScript, TypeScript, Rust, Go, C/C++, Java, PHP, C#, Ruby, Zig, HTML, CSS, SCSS, Markdown, Swift, plain text, and images
Project-URL: Homepage, https://github.com/mariusei/file-scanner-mcp
Project-URL: Repository, https://github.com/mariusei/file-scanner-mcp
Project-URL: Issues, https://github.com/mariusei/file-scanner-mcp/issues
Author: Marius Berge Eide
License: MIT
License-File: LICENSE
Keywords: code-analysis,file-scanner,mcp,structure-extraction,tree-sitter
Classifier: Development Status :: 4 - Beta
Classifier: Intended Audience :: Developers
Classifier: License :: OSI Approved :: MIT License
Classifier: Programming Language :: Python :: 3
Classifier: Programming Language :: Python :: 3.11
Classifier: Programming Language :: Python :: 3.12
Classifier: Programming Language :: Python :: 3.13
Classifier: Topic :: Software Development :: Libraries :: Python Modules
Requires-Python: >=3.11
Requires-Dist: fastmcp>=2.12.4
Requires-Dist: numpy>=1.24.0
Requires-Dist: pglast>=7.7
Requires-Dist: pillow>=10.0.0
Requires-Dist: tree-sitter-c-sharp>=0.23.0
Requires-Dist: tree-sitter-cpp>=0.23.0
Requires-Dist: tree-sitter-css>=0.23.0
Requires-Dist: tree-sitter-go>=0.23.3
Requires-Dist: tree-sitter-html>=0.23.0
Requires-Dist: tree-sitter-java>=0.23.2
Requires-Dist: tree-sitter-javascript>=0.23.1
Requires-Dist: tree-sitter-markdown>=0.3.2
Requires-Dist: tree-sitter-php>=0.23.4
Requires-Dist: tree-sitter-python>=0.23.6
Requires-Dist: tree-sitter-ruby>=0.23.0
Requires-Dist: tree-sitter-rust>=0.23.2
Requires-Dist: tree-sitter-scss>=1.0.0
Requires-Dist: tree-sitter-sql>=0.3.11
Requires-Dist: tree-sitter-swift>=0.0.1
Requires-Dist: tree-sitter-typescript>=0.23.2
Requires-Dist: tree-sitter-zig>=1.1.2
Requires-Dist: tree-sitter>=0.23.2
Requires-Dist: uvicorn>=0.32.1
